pybase16384/__init__.py
pybase16384/backends/__init__.py
pybase16384/backends/cffi/__init__.py
pybase16384/backends/cffi/_core.abi3.so
pybase16384/backends/cffi/build.py
pybase16384/backends/cython/__init__.py
pybase16384/backends/cython/_core.abi3.so
pybase16384/backends/cython/_core.c
pybase16384/backends/cython/_core.pxi
pybase16384/backends/cython/_core.pyx
pybase16384/backends/cython/base16384.pxd
pybase16384-0.3.9.dist-info/METADATA
pybase16384-0.3.9.dist-info/WHEEL
pybase16384-0.3.9.dist-info/top_level.txt
pybase16384-0.3.9.dist-info/RECORD
pybase16384-0.3.9.dist-info/licenses/LICENSE
